LICENSE
README.md
pyproject.toml
setup.py
nonebot_plugin_ds_baisuwen/__init__.py
nonebot_plugin_ds_baisuwen/config_loader.py
nonebot_plugin_ds_baisuwen/deepseek_service.py
nonebot_plugin_ds_baisuwen/message_handler.py
nonebot_plugin_ds_baisuwen/rate_limiter.py
nonebot_plugin_ds_baisuwen/redis_handler.py
nonebot_plugin_ds_baisuwen.egg-info/PKG-INFO
nonebot_plugin_ds_baisuwen.egg-info/SOURCES.txt
nonebot_plugin_ds_baisuwen.egg-info/dependency_links.txt
nonebot_plugin_ds_baisuwen.egg-info/not-zip-safe
nonebot_plugin_ds_baisuwen.egg-info/requires.txt
nonebot_plugin_ds_baisuwen.egg-info/top_level.txt
nonebot_plugin_ds_baisuwen/data/qq.json