Metadata-Version: 2.2
Name: nonebot-plugin-ds-baisuwen
Version: 1.1.7
Summary: 基于DeepSeek的智能聊天机器人，打造属于你的赛博群友
Author-email: LongYue <2279303156@qq.com>
Project-URL: homepage, https://github.com/Longxuanyue/nonebot_plugin_ds_baisuwen
Classifier: Programming Language :: Python :: 3
Classifier: License :: OSI Approved :: MIT License
Classifier: Operating System :: OS Independent
Requires-Python: >=3.8
License-File: LICENSE
Requires-Dist: nonebot2>=2.0.0
Requires-Dist: httpx[http2]>=0.23.0
Requires-Dist: tenacity>=8.2.2
Requires-Dist: redis>=4.5.1
Requires-Dist: nonebot-adapter-onebot>=2.0.0
Provides-Extra: onebot
Requires-Dist: nonebot-adapter-onebot-v11>=2.0.0; extra == "onebot"
Provides-Extra: dev
Requires-Dist: pytest>=7.0; extra == "dev"
Requires-Dist: pytest-asyncio>=0.21.0; extra == "dev"
Requires-Dist: black>=23.3.0; extra == "dev"
Requires-Dist: mypy>=1.3.0; extra == "dev"
